earnest/earnest.py
earnest/__init__.py
py_earnest-0.1.4.dist-info/DESCRIPTION.rst
py_earnest-0.1.4.dist-info/entry_points.txt
py_earnest-0.1.4.dist-info/METADATA
py_earnest-0.1.4.dist-info/metadata.json
py_earnest-0.1.4.dist-info/RECORD
py_earnest-0.1.4.dist-info/top_level.txt
py_earnest-0.1.4.dist-info/WHEEL
